odoo/addons/l10n_ro_hr/README.rst
odoo/addons/l10n_ro_hr/__init__.py
odoo/addons/l10n_ro_hr/__manifest__.py
odoo/addons/l10n_ro_hr/data/hr_demo.xml
odoo/addons/l10n_ro_hr/i18n/l10n_ro_hr.pot
odoo/addons/l10n_ro_hr/models/__init__.py
odoo/addons/l10n_ro_hr/models/hr_employee.py
odoo/addons/l10n_ro_hr/models/res_company.py
odoo/addons/l10n_ro_hr/security/ir.model.access.csv
odoo/addons/l10n_ro_hr/static/description/icon.png
odoo/addons/l10n_ro_hr/tests/__init__.py
odoo/addons/l10n_ro_hr/tests/test_hr_employee.py
odoo/addons/l10n_ro_hr/views/hr_employee_view.xml
odoo/addons/l10n_ro_hr/views/res_company_view.xml
odoo11_addon_l10n_ro_hr-11.0.1.0.0.99.dev10.dist-info/METADATA
odoo11_addon_l10n_ro_hr-11.0.1.0.0.99.dev10.dist-info/WHEEL
odoo11_addon_l10n_ro_hr-11.0.1.0.0.99.dev10.dist-info/top_level.txt
odoo11_addon_l10n_ro_hr-11.0.1.0.0.99.dev10.dist-info/RECORD
